pywordapi/__init__.py
pywordapi/requirements.txt
pywordapi/wordpress.py
pywordapi-1.0.9.dist-info/AUTHORS.rst
pywordapi-1.0.9.dist-info/LICENSE
pywordapi-1.0.9.dist-info/METADATA
pywordapi-1.0.9.dist-info/WHEEL
pywordapi-1.0.9.dist-info/top_level.txt
pywordapi-1.0.9.dist-info/RECORD
